awscurl/__init__.py
awscurl/__main__.py
awscurl/awscurl.py
awscurl/utils.py
awscurl-0.36.dist-info/LICENSE
awscurl-0.36.dist-info/METADATA
awscurl-0.36.dist-info/WHEEL
awscurl-0.36.dist-info/entry_points.txt
awscurl-0.36.dist-info/top_level.txt
awscurl-0.36.dist-info/RECORD
