Metadata-Version: 2.1
Name: awscurl
Version: 0.36
Summary: Curl like tool with AWS request signing
Home-page: http://github.com/okigan/awscurl
Author: Igor Okulist
Author-email: okigan@gmail.com
License: MIT
License-File: LICENSE
Requires-Dist: requests
Requires-Dist: configargparse
Requires-Dist: configparser
Requires-Dist: urllib3
Requires-Dist: botocore
Provides-Extra: awslibs
